fileargs/__init__.py
fileargs/command_line.py
fileargs-0.2.dist-info/LICENSE
fileargs-0.2.dist-info/METADATA
fileargs-0.2.dist-info/WHEEL
fileargs-0.2.dist-info/entry_points.txt
fileargs-0.2.dist-info/top_level.txt
fileargs-0.2.dist-info/RECORD
